pait/__init__.py
pait/__version__.py
pait/_pydanitc_adapter.py
pait/app/__init__.py
pait/app/any/__init__.py
pait/app/any/plugin/__init__.py
pait/app/any/plugin/auto_complete_json_resp.py
pait/app/any/plugin/cache_response.py
pait/app/any/plugin/check_json_resp.py
pait/app/any/plugin/mock_response.py
pait/app/any/plugin/unified_response.py
pait/app/any/plugin/util.py
pait/app/any/security/__init__.py
pait/app/any/security/api_key.py
pait/app/any/security/http.py
pait/app/any/security/oauth2.py
pait/app/any/security/util.py
pait/app/any/util.py
pait/app/auto_load_app.py
pait/app/base/__init__.py
pait/app/base/adapter/__init__.py
pait/app/base/adapter/request.py
pait/app/base/api_route.py
pait/app/base/app_helper.py
pait/app/base/security/__init__.py
pait/app/base/security/api_key.py
pait/app/base/security/base.py
pait/app/base/security/http.py
pait/app/base/security/oauth2.py
pait/app/base/security/util.py
pait/app/base/simple_route.py
pait/app/base/test_helper.py
pait/app/flask/__init__.py
pait/app/flask/_api_route.py
pait/app/flask/_app_helper.py
pait/app/flask/_load_app.py
pait/app/flask/_pait.py
pait/app/flask/_simple_route.py
pait/app/flask/_test_helper.py
pait/app/flask/adapter/__init__.py
pait/app/flask/adapter/attribute.py
pait/app/flask/adapter/exception.py
pait/app/flask/adapter/request.py
pait/app/flask/adapter/response.py
pait/app/flask/plugin/__init__.py
pait/app/flask/plugin/auto_complete_json_resp.py
pait/app/flask/plugin/cache_response.py
pait/app/flask/plugin/check_json_resp.py
pait/app/flask/plugin/mock_response.py
pait/app/flask/plugin/unified_response.py
pait/app/flask/security/__init__.py
pait/app/flask/security/api_key.py
pait/app/flask/security/http.py
pait/app/flask/security/oauth2.py
pait/app/flask/security/util.py
pait/app/sanic/__init__.py
pait/app/sanic/_api_route.py
pait/app/sanic/_app_helper.py
pait/app/sanic/_load_app.py
pait/app/sanic/_pait.py
pait/app/sanic/_simple_route.py
pait/app/sanic/_test_helper.py
pait-1.1.1.dist-info/LICENSE
pait-1.1.1.dist-info/METADATA
pait-1.1.1.dist-info/WHEEL
pait-1.1.1.dist-info/RECORD
