Metadata-Version: 2.1
Name: pait
Version: 1.1.1
Summary: Pait is a Python api tool. Pait enables your Python web framework to have type checking, parameter type conversion, interface document generation and can display your documents through Redoc or Swagger (power by inspect, pydantic)
Home-page: https://github.com/so1n/pait
License: Apache Software License
Author: So1n
Author-email: so1n897046026@gmail.com
Requires-Python: >=3.8.1,<4.0.0
Classifier: License :: Other/Proprietary License
Classifier: Programming Language :: Python :: 3
Classifier: Programming Language :: Python :: 3.9
Classifier: Programming Language :: Python :: 3.10
Classifier: Programming Language :: Python :: 3.11
Classifier: Programming Language :: Python :: 3.12
Provides-Extra: all
Provides-Extra: multipart
Provides-Extra: redis
Provides-Extra: streaming-form-data
Requires-Dist: any-api (==0.1.0.11)
Requires-Dist: multipart (>=1.1.0,<2.0.0) ; extra == "multipart"
Requires-Dist: redis (>=4.2.2,<5.0.0) ; extra == "redis" or extra == "all"
Requires-Dist: streaming_form_data (>=1.16.0,<2.0.0) ; extra == "streaming-form-data"
Project-URL: Changelog, https://github.com/so1n/pait/blob/master/CHANGELOG.md
Project-URL: Documentation, https://so1n.me/pait/
Project-URL: Repository, https://github.com/so1n/pait
Project-URL: Source, https://github.com/so1n/pait
Project-URL: Tracker, https://github.com/so1n/pait/issues
